odoo/addons/partner_search_alias/README.rst
odoo/addons/partner_search_alias/__init__.py
odoo/addons/partner_search_alias/__manifest__.py
odoo/addons/partner_search_alias/i18n/it.po
odoo/addons/partner_search_alias/i18n/partner_search_alias.pot
odoo/addons/partner_search_alias/models/__init__.py
odoo/addons/partner_search_alias/models/res_partner.py
odoo/addons/partner_search_alias/readme/DESCRIPTION.md
odoo/addons/partner_search_alias/static/description/icon.png
odoo/addons/partner_search_alias/static/description/index.html
odoo/addons/partner_search_alias/tests/__init__.py
odoo/addons/partner_search_alias/tests/test_partner_search_alias.py
odoo/addons/partner_search_alias/views/res_partner_views.xml
odoo_addon_partner_search_alias-18.0.1.0.0.2.dist-info/METADATA
odoo_addon_partner_search_alias-18.0.1.0.0.2.dist-info/WHEEL
odoo_addon_partner_search_alias-18.0.1.0.0.2.dist-info/top_level.txt
odoo_addon_partner_search_alias-18.0.1.0.0.2.dist-info/RECORD
